[
  {
    "project_id": "applied-history",
    "closure_lane": "runtime_deployment_validation",
    "vault_href": "vaults/applied-history/index.html",
    "required_slot_count": 4,
    "present_slot_count": 0,
    "validation_status": "evidence_missing",
    "promotion_allowed": "no",
    "vault_hash": "e3d317c295038395"
  },
  {
    "project_id": "native-aiprompt-eng",
    "closure_lane": "runtime_deployment_validation",
    "vault_href": "vaults/native-aiprompt-eng/index.html",
    "required_slot_count": 4,
    "present_slot_count": 0,
    "validation_status": "evidence_missing",
    "promotion_allowed": "no",
    "vault_hash": "72401738c7b42069"
  },
  {
    "project_id": "native-analyst-assurance-desk",
    "closure_lane": "runtime_deployment_validation",
    "vault_href": "vaults/native-analyst-assurance-desk/index.html",
    "required_slot_count": 4,
    "present_slot_count": 0,
    "validation_status": "evidence_missing",
    "promotion_allowed": "no",
    "vault_hash": "797fb2ff59105f3f"
  },
  {
    "project_id": "native-berlin",
    "closure_lane": "runtime_deployment_validation",
    "vault_href": "vaults/native-berlin/index.html",
    "required_slot_count": 4,
    "present_slot_count": 0,
    "validation_status": "evidence_missing",
    "promotion_allowed": "no",
    "vault_hash": "58bf209ab3a20b59"
  },
  {
    "project_id": "native-russia",
    "closure_lane": "runtime_deployment_validation",
    "vault_href": "vaults/native-russia/index.html",
    "required_slot_count": 4,
    "present_slot_count": 0,
    "validation_status": "evidence_missing",
    "promotion_allowed": "no",
    "vault_hash": "5426a0b96d172b69"
  },
  {
    "project_id": "native-russia-history-room",
    "closure_lane": "runtime_deployment_validation",
    "vault_href": "vaults/native-russia-history-room/index.html",
    "required_slot_count": 4,
    "present_slot_count": 0,
    "validation_status": "evidence_missing",
    "promotion_allowed": "no",
    "vault_hash": "803e5d9a6c7f7ccf"
  },
  {
    "project_id": "row6",
    "closure_lane": "runtime_deployment_validation",
    "vault_href": "vaults/row6/index.html",
    "required_slot_count": 4,
    "present_slot_count": 0,
    "validation_status": "evidence_missing",
    "promotion_allowed": "no",
    "vault_hash": "a26a6f77fd041678"
  },
  {
    "project_id": "cognitive-warfare",
    "closure_lane": "runtime_deployment_validation",
    "vault_href": "vaults/cognitive-warfare/index.html",
    "required_slot_count": 4,
    "present_slot_count": 0,
    "validation_status": "evidence_missing",
    "promotion_allowed": "no",
    "vault_hash": "1e34b3c522c620be"
  },
  {
    "project_id": "historical-studies",
    "closure_lane": "runtime_deployment_validation",
    "vault_href": "vaults/historical-studies/index.html",
    "required_slot_count": 4,
    "present_slot_count": 0,
    "validation_status": "evidence_missing",
    "promotion_allowed": "no",
    "vault_hash": "5c4c5c578c4aab25"
  },
  {
    "project_id": "ir-lexicon",
    "closure_lane": "runtime_deployment_validation",
    "vault_href": "vaults/ir-lexicon/index.html",
    "required_slot_count": 4,
    "present_slot_count": 0,
    "validation_status": "evidence_missing",
    "promotion_allowed": "no",
    "vault_hash": "9984a5c32a50152d"
  },
  {
    "project_id": "native-africa",
    "closure_lane": "runtime_deployment_validation",
    "vault_href": "vaults/native-africa/index.html",
    "required_slot_count": 4,
    "present_slot_count": 0,
    "validation_status": "evidence_missing",
    "promotion_allowed": "no",
    "vault_hash": "610473ff39d932cc"
  },
  {
    "project_id": "native-east-asia",
    "closure_lane": "runtime_deployment_validation",
    "vault_href": "vaults/native-east-asia/index.html",
    "required_slot_count": 4,
    "present_slot_count": 0,
    "validation_status": "evidence_missing",
    "promotion_allowed": "no",
    "vault_hash": "e7611c2b5a81b64b"
  },
  {
    "project_id": "native-mideast",
    "closure_lane": "runtime_deployment_validation",
    "vault_href": "vaults/native-mideast/index.html",
    "required_slot_count": 4,
    "present_slot_count": 0,
    "validation_status": "evidence_missing",
    "promotion_allowed": "no",
    "vault_hash": "bfa132a7440cca61"
  },
  {
    "project_id": "native-mongol",
    "closure_lane": "runtime_deployment_validation",
    "vault_href": "vaults/native-mongol/index.html",
    "required_slot_count": 4,
    "present_slot_count": 0,
    "validation_status": "evidence_missing",
    "promotion_allowed": "no",
    "vault_hash": "41a9946ea040b013"
  },
  {
    "project_id": "native-western",
    "closure_lane": "runtime_deployment_validation",
    "vault_href": "vaults/native-western/index.html",
    "required_slot_count": 4,
    "present_slot_count": 0,
    "validation_status": "evidence_missing",
    "promotion_allowed": "no",
    "vault_hash": "cf3f9bb1f0073cd4"
  },
  {
    "project_id": "russia-desk",
    "closure_lane": "runtime_deployment_validation",
    "vault_href": "vaults/russia-desk/index.html",
    "required_slot_count": 4,
    "present_slot_count": 0,
    "validation_status": "evidence_missing",
    "promotion_allowed": "no",
    "vault_hash": "be7169255f6a5264"
  },
  {
    "project_id": "analytical-methodology",
    "closure_lane": "runtime_deployment_validation",
    "vault_href": "vaults/analytical-methodology/index.html",
    "required_slot_count": 4,
    "present_slot_count": 0,
    "validation_status": "evidence_missing",
    "promotion_allowed": "no",
    "vault_hash": "f43f0b31a5c84d38"
  },
  {
    "project_id": "regional-studies",
    "closure_lane": "runtime_deployment_validation",
    "vault_href": "vaults/regional-studies/index.html",
    "required_slot_count": 4,
    "present_slot_count": 0,
    "validation_status": "evidence_missing",
    "promotion_allowed": "no",
    "vault_hash": "41467bd677f7abd9"
  },
  {
    "project_id": "decision-advantage-system",
    "closure_lane": "runtime_deployment_validation",
    "vault_href": "vaults/decision-advantage-system/index.html",
    "required_slot_count": 4,
    "present_slot_count": 0,
    "validation_status": "evidence_missing",
    "promotion_allowed": "no",
    "vault_hash": "84aa9013a2129b47"
  },
  {
    "project_id": "mb-dialectic-engine-room-pass1-handoff",
    "closure_lane": "runtime_deployment_validation",
    "vault_href": "vaults/mb-dialectic-engine-room-pass1-handoff/index.html",
    "required_slot_count": 4,
    "present_slot_count": 0,
    "validation_status": "evidence_missing",
    "promotion_allowed": "no",
    "vault_hash": "1e3a1cd8d0c9f7bf"
  },
  {
    "project_id": "native-russia-security-desk",
    "closure_lane": "runtime_deployment_validation",
    "vault_href": "vaults/native-russia-security-desk/index.html",
    "required_slot_count": 4,
    "present_slot_count": 0,
    "validation_status": "evidence_missing",
    "promotion_allowed": "no",
    "vault_hash": "79119047a2f999d6"
  },
  {
    "project_id": "mb-infragard-handoff",
    "closure_lane": "runtime_deployment_validation",
    "vault_href": "vaults/mb-infragard-handoff/index.html",
    "required_slot_count": 4,
    "present_slot_count": 0,
    "validation_status": "evidence_missing",
    "promotion_allowed": "no",
    "vault_hash": "073ffba6ff70362d"
  },
  {
    "project_id": "mb-insinuationengineroom-handoff-done",
    "closure_lane": "runtime_deployment_validation",
    "vault_href": "vaults/mb-insinuationengineroom-handoff-done/index.html",
    "required_slot_count": 4,
    "present_slot_count": 0,
    "validation_status": "evidence_missing",
    "promotion_allowed": "no",
    "vault_hash": "1661266334b7ac07"
  },
  {
    "project_id": "mb-nik-handoff-v1",
    "closure_lane": "source_verification_external_review",
    "vault_href": "vaults/mb-nik-handoff-v1/index.html",
    "required_slot_count": 4,
    "present_slot_count": 0,
    "validation_status": "evidence_missing",
    "promotion_allowed": "no",
    "vault_hash": "61d6874bda92f51b"
  },
  {
    "project_id": "mb-russia-intelligence-analysis-final-handoff",
    "closure_lane": "source_verification_external_review",
    "vault_href": "vaults/mb-russia-intelligence-analysis-final-handoff/index.html",
    "required_slot_count": 4,
    "present_slot_count": 0,
    "validation_status": "evidence_missing",
    "promotion_allowed": "no",
    "vault_hash": "ac2282da940d552b"
  },
  {
    "project_id": "mb-russian-reference-handoff-final",
    "closure_lane": "source_verification_external_review",
    "vault_href": "vaults/mb-russian-reference-handoff-final/index.html",
    "required_slot_count": 4,
    "present_slot_count": 0,
    "validation_status": "evidence_missing",
    "promotion_allowed": "no",
    "vault_hash": "16af7ae0ee16a57f"
  },
  {
    "project_id": "mb-visible-chat-handoff-package",
    "closure_lane": "source_verification_external_review",
    "vault_href": "vaults/mb-visible-chat-handoff-package/index.html",
    "required_slot_count": 4,
    "present_slot_count": 0,
    "validation_status": "evidence_missing",
    "promotion_allowed": "no",
    "vault_hash": "d71e863b29c5c496"
  },
  {
    "project_id": "native-aigov-nav",
    "closure_lane": "source_verification_external_review",
    "vault_href": "vaults/native-aigov-nav/index.html",
    "required_slot_count": 4,
    "present_slot_count": 0,
    "validation_status": "evidence_missing",
    "promotion_allowed": "no",
    "vault_hash": "05c6af4e6d278003"
  },
  {
    "project_id": "native-aiintel-cycle",
    "closure_lane": "source_verification_external_review",
    "vault_href": "vaults/native-aiintel-cycle/index.html",
    "required_slot_count": 4,
    "present_slot_count": 0,
    "validation_status": "evidence_missing",
    "promotion_allowed": "no",
    "vault_hash": "8e529a6302fc9a75"
  },
  {
    "project_id": "native-aiknowledge-prod",
    "closure_lane": "source_verification_external_review",
    "vault_href": "vaults/native-aiknowledge-prod/index.html",
    "required_slot_count": 4,
    "present_slot_count": 0,
    "validation_status": "evidence_missing",
    "promotion_allowed": "no",
    "vault_hash": "3db81eeb49486d43"
  },
  {
    "project_id": "native-aishared-instruments",
    "closure_lane": "source_verification_external_review",
    "vault_href": "vaults/native-aishared-instruments/index.html",
    "required_slot_count": 4,
    "present_slot_count": 0,
    "validation_status": "evidence_missing",
    "promotion_allowed": "no",
    "vault_hash": "fb8c4c053c5e6020"
  },
  {
    "project_id": "native-cicc",
    "closure_lane": "source_verification_external_review",
    "vault_href": "vaults/native-cicc/index.html",
    "required_slot_count": 4,
    "present_slot_count": 0,
    "validation_status": "evidence_missing",
    "promotion_allowed": "no",
    "vault_hash": "7c10439c9eed98bf"
  },
  {
    "project_id": "native-crusades",
    "closure_lane": "source_verification_external_review",
    "vault_href": "vaults/native-crusades/index.html",
    "required_slot_count": 4,
    "present_slot_count": 0,
    "validation_status": "evidence_missing",
    "promotion_allowed": "no",
    "vault_hash": "2bd242b39bfbc853"
  },
  {
    "project_id": "native-peace",
    "closure_lane": "source_verification_external_review",
    "vault_href": "vaults/native-peace/index.html",
    "required_slot_count": 4,
    "present_slot_count": 0,
    "validation_status": "evidence_missing",
    "promotion_allowed": "no",
    "vault_hash": "2ecc16613e395338"
  },
  {
    "project_id": "native-war-theory",
    "closure_lane": "source_verification_external_review",
    "vault_href": "vaults/native-war-theory/index.html",
    "required_slot_count": 4,
    "present_slot_count": 0,
    "validation_status": "evidence_missing",
    "promotion_allowed": "no",
    "vault_hash": "caa1ccc96969820d"
  },
  {
    "project_id": "cognitive-firewall-instruments",
    "closure_lane": "publication_readiness_review",
    "vault_href": "vaults/cognitive-firewall-instruments/index.html",
    "required_slot_count": 4,
    "present_slot_count": 0,
    "validation_status": "evidence_missing",
    "promotion_allowed": "no",
    "vault_hash": "5b3c082461b528d1"
  },
  {
    "project_id": "master-bundle-atlas",
    "closure_lane": "source_verification_external_review",
    "vault_href": "vaults/master-bundle-atlas/index.html",
    "required_slot_count": 4,
    "present_slot_count": 0,
    "validation_status": "evidence_missing",
    "promotion_allowed": "no",
    "vault_hash": "17c385ce9b6b97f7"
  },
  {
    "project_id": "native-amfp",
    "closure_lane": "source_verification_external_review",
    "vault_href": "vaults/native-amfp/index.html",
    "required_slot_count": 4,
    "present_slot_count": 0,
    "validation_status": "evidence_missing",
    "promotion_allowed": "no",
    "vault_hash": "572b1ad2e37f5a77"
  },
  {
    "project_id": "native-trilogy-showcase",
    "closure_lane": "manuscript_editorial_completion",
    "vault_href": "vaults/native-trilogy-showcase/index.html",
    "required_slot_count": 4,
    "present_slot_count": 0,
    "validation_status": "evidence_missing",
    "promotion_allowed": "no",
    "vault_hash": "57495639306417f6"
  },
  {
    "project_id": "native-trilogy-showcase-atlas",
    "closure_lane": "manuscript_editorial_completion",
    "vault_href": "vaults/native-trilogy-showcase-atlas/index.html",
    "required_slot_count": 4,
    "present_slot_count": 0,
    "validation_status": "evidence_missing",
    "promotion_allowed": "no",
    "vault_hash": "bd42d6815ffd14d5"
  },
  {
    "project_id": "reflexive-control-chamber",
    "closure_lane": "source_verification_external_review",
    "vault_href": "vaults/reflexive-control-chamber/index.html",
    "required_slot_count": 4,
    "present_slot_count": 0,
    "validation_status": "evidence_missing",
    "promotion_allowed": "no",
    "vault_hash": "4fdc404895318f4e"
  },
  {
    "project_id": "row2",
    "closure_lane": "publication_readiness_review",
    "vault_href": "vaults/row2/index.html",
    "required_slot_count": 4,
    "present_slot_count": 0,
    "validation_status": "evidence_missing",
    "promotion_allowed": "no",
    "vault_hash": "142c558799259fae"
  },
  {
    "project_id": "trilogy",
    "closure_lane": "manuscript_editorial_completion",
    "vault_href": "vaults/trilogy/index.html",
    "required_slot_count": 4,
    "present_slot_count": 0,
    "validation_status": "evidence_missing",
    "promotion_allowed": "no",
    "vault_hash": "04bfcc293628b6c6"
  },
  {
    "project_id": "bias-atlas",
    "closure_lane": "live_case_calibration",
    "vault_href": "vaults/bias-atlas/index.html",
    "required_slot_count": 4,
    "present_slot_count": 0,
    "validation_status": "evidence_missing",
    "promotion_allowed": "no",
    "vault_hash": "8456eff17cc9950e"
  },
  {
    "project_id": "genocide-lab",
    "closure_lane": "live_case_calibration",
    "vault_href": "vaults/genocide-lab/index.html",
    "required_slot_count": 4,
    "present_slot_count": 0,
    "validation_status": "evidence_missing",
    "promotion_allowed": "no",
    "vault_hash": "31fbead859d6fe97"
  },
  {
    "project_id": "mb-ic-analytic-technique-compendium-bundle-v0-1-v1-3",
    "closure_lane": "manuscript_editorial_completion",
    "vault_href": "vaults/mb-ic-analytic-technique-compendium-bundle-v0-1-v1-3/index.html",
    "required_slot_count": 4,
    "present_slot_count": 0,
    "validation_status": "evidence_missing",
    "promotion_allowed": "no",
    "vault_hash": "18241752c8dff1bf"
  },
  {
    "project_id": "native-aifailure-tax",
    "closure_lane": "live_case_calibration",
    "vault_href": "vaults/native-aifailure-tax/index.html",
    "required_slot_count": 4,
    "present_slot_count": 0,
    "validation_status": "evidence_missing",
    "promotion_allowed": "no",
    "vault_hash": "e6cf4d1643d59f20"
  },
  {
    "project_id": "native-aimodel-assess",
    "closure_lane": "source_verification_external_review",
    "vault_href": "vaults/native-aimodel-assess/index.html",
    "required_slot_count": 4,
    "present_slot_count": 0,
    "validation_status": "evidence_missing",
    "promotion_allowed": "no",
    "vault_hash": "0c0378d37046577e"
  },
  {
    "project_id": "native-aiosintnarr",
    "closure_lane": "source_verification_external_review",
    "vault_href": "vaults/native-aiosintnarr/index.html",
    "required_slot_count": 4,
    "present_slot_count": 0,
    "validation_status": "evidence_missing",
    "promotion_allowed": "no",
    "vault_hash": "1d75b633eb1e2267"
  },
  {
    "project_id": "native-atanalysis",
    "closure_lane": "live_case_calibration",
    "vault_href": "vaults/native-atanalysis/index.html",
    "required_slot_count": 4,
    "present_slot_count": 0,
    "validation_status": "evidence_missing",
    "promotion_allowed": "no",
    "vault_hash": "136e535b7ae89f64"
  },
  {
    "project_id": "native-cmanalysis",
    "closure_lane": "live_case_calibration",
    "vault_href": "vaults/native-cmanalysis/index.html",
    "required_slot_count": 4,
    "present_slot_count": 0,
    "validation_status": "evidence_missing",
    "promotion_allowed": "no",
    "vault_hash": "401e2cecb821dc7b"
  },
  {
    "project_id": "native-cyanalysis",
    "closure_lane": "live_case_calibration",
    "vault_href": "vaults/native-cyanalysis/index.html",
    "required_slot_count": 4,
    "present_slot_count": 0,
    "validation_status": "evidence_missing",
    "promotion_allowed": "no",
    "vault_hash": "959b863638baa9fc"
  },
  {
    "project_id": "native-ddianalysis",
    "closure_lane": "live_case_calibration",
    "vault_href": "vaults/native-ddianalysis/index.html",
    "required_slot_count": 4,
    "present_slot_count": 0,
    "validation_status": "evidence_missing",
    "promotion_allowed": "no",
    "vault_hash": "b77c50647f1497db"
  },
  {
    "project_id": "native-etanalysis",
    "closure_lane": "live_case_calibration",
    "vault_href": "vaults/native-etanalysis/index.html",
    "required_slot_count": 4,
    "present_slot_count": 0,
    "validation_status": "evidence_missing",
    "promotion_allowed": "no",
    "vault_hash": "30fb1373b3baadba"
  },
  {
    "project_id": "native-fwanalysis",
    "closure_lane": "live_case_calibration",
    "vault_href": "vaults/native-fwanalysis/index.html",
    "required_slot_count": 4,
    "present_slot_count": 0,
    "validation_status": "evidence_missing",
    "promotion_allowed": "no",
    "vault_hash": "c3df27c889b247f3"
  },
  {
    "project_id": "native-hsanalysis",
    "closure_lane": "live_case_calibration",
    "vault_href": "vaults/native-hsanalysis/index.html",
    "required_slot_count": 4,
    "present_slot_count": 0,
    "validation_status": "evidence_missing",
    "promotion_allowed": "no",
    "vault_hash": "f6b0472bb0ad6626"
  },
  {
    "project_id": "native-icanalysis",
    "closure_lane": "live_case_calibration",
    "vault_href": "vaults/native-icanalysis/index.html",
    "required_slot_count": 4,
    "present_slot_count": 0,
    "validation_status": "evidence_missing",
    "promotion_allowed": "no",
    "vault_hash": "bfcb13361d5f1224"
  },
  {
    "project_id": "native-psanalysis",
    "closure_lane": "live_case_calibration",
    "vault_href": "vaults/native-psanalysis/index.html",
    "required_slot_count": 4,
    "present_slot_count": 0,
    "validation_status": "evidence_missing",
    "promotion_allowed": "no",
    "vault_hash": "01279c7b5fc799f8"
  },
  {
    "project_id": "native-wargaming",
    "closure_lane": "source_verification_external_review",
    "vault_href": "vaults/native-wargaming/index.html",
    "required_slot_count": 4,
    "present_slot_count": 0,
    "validation_status": "evidence_missing",
    "promotion_allowed": "no",
    "vault_hash": "ba0c7b29ab4dae12"
  },
  {
    "project_id": "wargaming",
    "closure_lane": "source_verification_external_review",
    "vault_href": "vaults/wargaming/index.html",
    "required_slot_count": 4,
    "present_slot_count": 0,
    "validation_status": "evidence_missing",
    "promotion_allowed": "no",
    "vault_hash": "755dd73f5825c8bf"
  },
  {
    "project_id": "critical-functions-observatory",
    "closure_lane": "source_verification_external_review",
    "vault_href": "vaults/critical-functions-observatory/index.html",
    "required_slot_count": 4,
    "present_slot_count": 0,
    "validation_status": "evidence_missing",
    "promotion_allowed": "no",
    "vault_hash": "3b4fb0958a6b4cde"
  },
  {
    "project_id": "mb-russia-security-handoff-packet-done",
    "closure_lane": "source_verification_external_review",
    "vault_href": "vaults/mb-russia-security-handoff-packet-done/index.html",
    "required_slot_count": 4,
    "present_slot_count": 0,
    "validation_status": "evidence_missing",
    "promotion_allowed": "no",
    "vault_hash": "866368f0374c5e6b"
  },
  {
    "project_id": "mb-narrative-furnace-handoff-pack-2026-04-14",
    "closure_lane": "source_verification_external_review",
    "vault_href": "vaults/mb-narrative-furnace-handoff-pack-2026-04-14/index.html",
    "required_slot_count": 4,
    "present_slot_count": 0,
    "validation_status": "evidence_missing",
    "promotion_allowed": "no",
    "vault_hash": "8f27b059051f600c"
  },
  {
    "project_id": "mb-redteamlab-proper-handoff-zip-2026-04-14",
    "closure_lane": "source_verification_external_review",
    "vault_href": "vaults/mb-redteamlab-proper-handoff-zip-2026-04-14/index.html",
    "required_slot_count": 4,
    "present_slot_count": 0,
    "validation_status": "evidence_missing",
    "promotion_allowed": "no",
    "vault_hash": "29c440f2353fd637"
  },
  {
    "project_id": "mb-six-project-hardening-handoff-done-v1",
    "closure_lane": "source_verification_external_review",
    "vault_href": "vaults/mb-six-project-hardening-handoff-done-v1/index.html",
    "required_slot_count": 4,
    "present_slot_count": 0,
    "validation_status": "evidence_missing",
    "promotion_allowed": "no",
    "vault_hash": "237cc6adc80d70d6"
  },
  {
    "project_id": "mb-speechwriting-handoff-packet",
    "closure_lane": "source_verification_external_review",
    "vault_href": "vaults/mb-speechwriting-handoff-packet/index.html",
    "required_slot_count": 4,
    "present_slot_count": 0,
    "validation_status": "evidence_missing",
    "promotion_allowed": "no",
    "vault_hash": "cd30ad303ca3d1a8"
  },
  {
    "project_id": "mb-cognitive-firewalls-foundry-handoff-v1",
    "closure_lane": "source_verification_external_review",
    "vault_href": "vaults/mb-cognitive-firewalls-foundry-handoff-v1/index.html",
    "required_slot_count": 4,
    "present_slot_count": 0,
    "validation_status": "evidence_missing",
    "promotion_allowed": "no",
    "vault_hash": "493e4679900437ff"
  },
  {
    "project_id": "mb-redteamlab-packet1-proper-handoff-done",
    "closure_lane": "source_verification_external_review",
    "vault_href": "vaults/mb-redteamlab-packet1-proper-handoff-done/index.html",
    "required_slot_count": 4,
    "present_slot_count": 0,
    "validation_status": "evidence_missing",
    "promotion_allowed": "no",
    "vault_hash": "88229d85872f0154"
  },
  {
    "project_id": "native-london",
    "closure_lane": "source_verification_external_review",
    "vault_href": "vaults/native-london/index.html",
    "required_slot_count": 4,
    "present_slot_count": 0,
    "validation_status": "evidence_missing",
    "promotion_allowed": "no",
    "vault_hash": "ec08c37a7af11fcc"
  },
  {
    "project_id": "mb-hearthglass-handoff-v1",
    "closure_lane": "source_verification_external_review",
    "vault_href": "vaults/mb-hearthglass-handoff-v1/index.html",
    "required_slot_count": 4,
    "present_slot_count": 0,
    "validation_status": "evidence_missing",
    "promotion_allowed": "no",
    "vault_hash": "fb20ef7d3c5a97c6"
  },
  {
    "project_id": "mb-isc-symposium-command-room-handoff-pass3-done",
    "closure_lane": "source_verification_external_review",
    "vault_href": "vaults/mb-isc-symposium-command-room-handoff-pass3-done/index.html",
    "required_slot_count": 4,
    "present_slot_count": 0,
    "validation_status": "evidence_missing",
    "promotion_allowed": "no",
    "vault_hash": "753c26768d323b8c"
  },
  {
    "project_id": "mb-the-interval-chamber-of-refraction-handoff-v1",
    "closure_lane": "source_verification_external_review",
    "vault_href": "vaults/mb-the-interval-chamber-of-refraction-handoff-v1/index.html",
    "required_slot_count": 4,
    "present_slot_count": 0,
    "validation_status": "evidence_missing",
    "promotion_allowed": "no",
    "vault_hash": "f9028b45a84965fe"
  },
  {
    "project_id": "mb-counter-idiom-lab-proper-handoff-done",
    "closure_lane": "source_verification_external_review",
    "vault_href": "vaults/mb-counter-idiom-lab-proper-handoff-done/index.html",
    "required_slot_count": 4,
    "present_slot_count": 0,
    "validation_status": "evidence_missing",
    "promotion_allowed": "no",
    "vault_hash": "d8ea30056fed33d1"
  },
  {
    "project_id": "mb-foreign-affairs-lexicon-handoff-v1",
    "closure_lane": "source_verification_external_review",
    "vault_href": "vaults/mb-foreign-affairs-lexicon-handoff-v1/index.html",
    "required_slot_count": 4,
    "present_slot_count": 0,
    "validation_status": "evidence_missing",
    "promotion_allowed": "no",
    "vault_hash": "190ec81f8718f0a3"
  },
  {
    "project_id": "mb-georgetown-ic-handoff-done",
    "closure_lane": "source_verification_external_review",
    "vault_href": "vaults/mb-georgetown-ic-handoff-done/index.html",
    "required_slot_count": 4,
    "present_slot_count": 0,
    "validation_status": "evidence_missing",
    "promotion_allowed": "no",
    "vault_hash": "5b2bda70cc3e91c2"
  },
  {
    "project_id": "mb-gotham-lossless-replacement-archive-2026-04-15",
    "closure_lane": "source_verification_external_review",
    "vault_href": "vaults/mb-gotham-lossless-replacement-archive-2026-04-15/index.html",
    "required_slot_count": 4,
    "present_slot_count": 0,
    "validation_status": "evidence_missing",
    "promotion_allowed": "no",
    "vault_hash": "16d44338ffd881b9"
  },
  {
    "project_id": "mb-internal-operating-support-003",
    "closure_lane": "source_verification_external_review",
    "vault_href": "vaults/mb-internal-operating-support-003/index.html",
    "required_slot_count": 4,
    "present_slot_count": 0,
    "validation_status": "evidence_missing",
    "promotion_allowed": "no",
    "vault_hash": "499925e3863c0074"
  },
  {
    "project_id": "mb-internal-operating-support-004",
    "closure_lane": "source_verification_external_review",
    "vault_href": "vaults/mb-internal-operating-support-004/index.html",
    "required_slot_count": 4,
    "present_slot_count": 0,
    "validation_status": "evidence_missing",
    "promotion_allowed": "no",
    "vault_hash": "a52fae3f73476ca4"
  },
  {
    "project_id": "mb-internal-operating-support-007",
    "closure_lane": "source_verification_external_review",
    "vault_href": "vaults/mb-internal-operating-support-007/index.html",
    "required_slot_count": 4,
    "present_slot_count": 0,
    "validation_status": "evidence_missing",
    "promotion_allowed": "no",
    "vault_hash": "2eb9a07ce2919234"
  },
  {
    "project_id": "mb-internal-operating-support-008",
    "closure_lane": "source_verification_external_review",
    "vault_href": "vaults/mb-internal-operating-support-008/index.html",
    "required_slot_count": 4,
    "present_slot_count": 0,
    "validation_status": "evidence_missing",
    "promotion_allowed": "no",
    "vault_hash": "14837fe4a07fd5b3"
  },
  {
    "project_id": "mb-internal-operating-support-011",
    "closure_lane": "source_verification_external_review",
    "vault_href": "vaults/mb-internal-operating-support-011/index.html",
    "required_slot_count": 4,
    "present_slot_count": 0,
    "validation_status": "evidence_missing",
    "promotion_allowed": "no",
    "vault_hash": "51561de615be8308"
  },
  {
    "project_id": "mb-internal-operating-support-012",
    "closure_lane": "source_verification_external_review",
    "vault_href": "vaults/mb-internal-operating-support-012/index.html",
    "required_slot_count": 4,
    "present_slot_count": 0,
    "validation_status": "evidence_missing",
    "promotion_allowed": "no",
    "vault_hash": "0bb376b1a3f15eb9"
  },
  {
    "project_id": "mb-internal-operating-support-015",
    "closure_lane": "source_verification_external_review",
    "vault_href": "vaults/mb-internal-operating-support-015/index.html",
    "required_slot_count": 4,
    "present_slot_count": 0,
    "validation_status": "evidence_missing",
    "promotion_allowed": "no",
    "vault_hash": "4605ed79e2ea7f60"
  },
  {
    "project_id": "mb-internal-operating-support-016",
    "closure_lane": "source_verification_external_review",
    "vault_href": "vaults/mb-internal-operating-support-016/index.html",
    "required_slot_count": 4,
    "present_slot_count": 0,
    "validation_status": "evidence_missing",
    "promotion_allowed": "no",
    "vault_hash": "8e5b36750e9e8777"
  },
  {
    "project_id": "mb-internal-operating-support-019",
    "closure_lane": "source_verification_external_review",
    "vault_href": "vaults/mb-internal-operating-support-019/index.html",
    "required_slot_count": 4,
    "present_slot_count": 0,
    "validation_status": "evidence_missing",
    "promotion_allowed": "no",
    "vault_hash": "5c3b61a1448abee1"
  },
  {
    "project_id": "mb-internal-operating-support-020",
    "closure_lane": "source_verification_external_review",
    "vault_href": "vaults/mb-internal-operating-support-020/index.html",
    "required_slot_count": 4,
    "present_slot_count": 0,
    "validation_status": "evidence_missing",
    "promotion_allowed": "no",
    "vault_hash": "833cd3f254adc458"
  },
  {
    "project_id": "mb-internal-operating-support-023",
    "closure_lane": "source_verification_external_review",
    "vault_href": "vaults/mb-internal-operating-support-023/index.html",
    "required_slot_count": 4,
    "present_slot_count": 0,
    "validation_status": "evidence_missing",
    "promotion_allowed": "no",
    "vault_hash": "085ee14a446073f5"
  },
  {
    "project_id": "mb-internal-operating-support-024",
    "closure_lane": "source_verification_external_review",
    "vault_href": "vaults/mb-internal-operating-support-024/index.html",
    "required_slot_count": 4,
    "present_slot_count": 0,
    "validation_status": "evidence_missing",
    "promotion_allowed": "no",
    "vault_hash": "9d98b53ff6142498"
  },
  {
    "project_id": "mb-internal-operating-support-027",
    "closure_lane": "source_verification_external_review",
    "vault_href": "vaults/mb-internal-operating-support-027/index.html",
    "required_slot_count": 4,
    "present_slot_count": 0,
    "validation_status": "evidence_missing",
    "promotion_allowed": "no",
    "vault_hash": "c0479e14bfe25b0a"
  },
  {
    "project_id": "mb-internal-operating-support-028",
    "closure_lane": "source_verification_external_review",
    "vault_href": "vaults/mb-internal-operating-support-028/index.html",
    "required_slot_count": 4,
    "present_slot_count": 0,
    "validation_status": "evidence_missing",
    "promotion_allowed": "no",
    "vault_hash": "13d877e116dc431e"
  },
  {
    "project_id": "mb-internal-operating-support-031",
    "closure_lane": "source_verification_external_review",
    "vault_href": "vaults/mb-internal-operating-support-031/index.html",
    "required_slot_count": 4,
    "present_slot_count": 0,
    "validation_status": "evidence_missing",
    "promotion_allowed": "no",
    "vault_hash": "5b940326f0d8a035"
  },
  {
    "project_id": "mb-internal-operating-support-032",
    "closure_lane": "source_verification_external_review",
    "vault_href": "vaults/mb-internal-operating-support-032/index.html",
    "required_slot_count": 4,
    "present_slot_count": 0,
    "validation_status": "evidence_missing",
    "promotion_allowed": "no",
    "vault_hash": "861d7e447082bc83"
  },
  {
    "project_id": "mb-internal-operating-support-035",
    "closure_lane": "source_verification_external_review",
    "vault_href": "vaults/mb-internal-operating-support-035/index.html",
    "required_slot_count": 4,
    "present_slot_count": 0,
    "validation_status": "evidence_missing",
    "promotion_allowed": "no",
    "vault_hash": "76e7315c0d5c8ad4"
  },
  {
    "project_id": "mb-internal-operating-support-036",
    "closure_lane": "source_verification_external_review",
    "vault_href": "vaults/mb-internal-operating-support-036/index.html",
    "required_slot_count": 4,
    "present_slot_count": 0,
    "validation_status": "evidence_missing",
    "promotion_allowed": "no",
    "vault_hash": "d96bcde082777b31"
  },
  {
    "project_id": "mb-sophisticated-expression-lexicon-handoff",
    "closure_lane": "source_verification_external_review",
    "vault_href": "vaults/mb-sophisticated-expression-lexicon-handoff/index.html",
    "required_slot_count": 4,
    "present_slot_count": 0,
    "validation_status": "evidence_missing",
    "promotion_allowed": "no",
    "vault_hash": "540550824ef404a1"
  },
  {
    "project_id": "mb-ic-analyst-portfolio-handoff-pass1",
    "closure_lane": "source_verification_external_review",
    "vault_href": "vaults/mb-ic-analyst-portfolio-handoff-pass1/index.html",
    "required_slot_count": 4,
    "present_slot_count": 0,
    "validation_status": "evidence_missing",
    "promotion_allowed": "no",
    "vault_hash": "7d86a3827511fbe5"
  },
  {
    "project_id": "mb-individual-democratic-dialectic-final-handoff-done",
    "closure_lane": "source_verification_external_review",
    "vault_href": "vaults/mb-individual-democratic-dialectic-final-handoff-done/index.html",
    "required_slot_count": 4,
    "present_slot_count": 0,
    "validation_status": "evidence_missing",
    "promotion_allowed": "no",
    "vault_hash": "89e6123d2da03d08"
  },
  {
    "project_id": "mb-ukraine-handoff-packet",
    "closure_lane": "source_verification_external_review",
    "vault_href": "vaults/mb-ukraine-handoff-packet/index.html",
    "required_slot_count": 4,
    "present_slot_count": 0,
    "validation_status": "evidence_missing",
    "promotion_allowed": "no",
    "vault_hash": "5629123b08bfd063"
  },
  {
    "project_id": "mb-briefingforgeroom-handoff-pass4-done",
    "closure_lane": "source_verification_external_review",
    "vault_href": "vaults/mb-briefingforgeroom-handoff-pass4-done/index.html",
    "required_slot_count": 4,
    "present_slot_count": 0,
    "validation_status": "evidence_missing",
    "promotion_allowed": "no",
    "vault_hash": "af188b2f6bc00539"
  },
  {
    "project_id": "mb-comparative-genocide-systems-lab-handoff-v1-0",
    "closure_lane": "source_verification_external_review",
    "vault_href": "vaults/mb-comparative-genocide-systems-lab-handoff-v1-0/index.html",
    "required_slot_count": 4,
    "present_slot_count": 0,
    "validation_status": "evidence_missing",
    "promotion_allowed": "no",
    "vault_hash": "2fe1af097577c033"
  },
  {
    "project_id": "mb-comparative-rhetoric-final",
    "closure_lane": "source_verification_external_review",
    "vault_href": "vaults/mb-comparative-rhetoric-final/index.html",
    "required_slot_count": 4,
    "present_slot_count": 0,
    "validation_status": "evidence_missing",
    "promotion_allowed": "no",
    "vault_hash": "53f9e1fa82b0526d"
  },
  {
    "project_id": "mb-fractal-keep-handoff-v1",
    "closure_lane": "source_verification_external_review",
    "vault_href": "vaults/mb-fractal-keep-handoff-v1/index.html",
    "required_slot_count": 4,
    "present_slot_count": 0,
    "validation_status": "evidence_missing",
    "promotion_allowed": "no",
    "vault_hash": "b6a796591e90dab5"
  },
  {
    "project_id": "mb-internal-operating-support-001",
    "closure_lane": "source_verification_external_review",
    "vault_href": "vaults/mb-internal-operating-support-001/index.html",
    "required_slot_count": 4,
    "present_slot_count": 0,
    "validation_status": "evidence_missing",
    "promotion_allowed": "no",
    "vault_hash": "40648d9b512229c8"
  },
  {
    "project_id": "mb-internal-operating-support-002",
    "closure_lane": "source_verification_external_review",
    "vault_href": "vaults/mb-internal-operating-support-002/index.html",
    "required_slot_count": 4,
    "present_slot_count": 0,
    "validation_status": "evidence_missing",
    "promotion_allowed": "no",
    "vault_hash": "fdb0d7324b9c74cc"
  },
  {
    "project_id": "mb-internal-operating-support-005",
    "closure_lane": "source_verification_external_review",
    "vault_href": "vaults/mb-internal-operating-support-005/index.html",
    "required_slot_count": 4,
    "present_slot_count": 0,
    "validation_status": "evidence_missing",
    "promotion_allowed": "no",
    "vault_hash": "4405fe26600e51b9"
  },
  {
    "project_id": "mb-internal-operating-support-006",
    "closure_lane": "source_verification_external_review",
    "vault_href": "vaults/mb-internal-operating-support-006/index.html",
    "required_slot_count": 4,
    "present_slot_count": 0,
    "validation_status": "evidence_missing",
    "promotion_allowed": "no",
    "vault_hash": "025a9fce4aabe55e"
  },
  {
    "project_id": "mb-internal-operating-support-009",
    "closure_lane": "source_verification_external_review",
    "vault_href": "vaults/mb-internal-operating-support-009/index.html",
    "required_slot_count": 4,
    "present_slot_count": 0,
    "validation_status": "evidence_missing",
    "promotion_allowed": "no",
    "vault_hash": "07439e1dca07438e"
  },
  {
    "project_id": "mb-internal-operating-support-010",
    "closure_lane": "source_verification_external_review",
    "vault_href": "vaults/mb-internal-operating-support-010/index.html",
    "required_slot_count": 4,
    "present_slot_count": 0,
    "validation_status": "evidence_missing",
    "promotion_allowed": "no",
    "vault_hash": "f7035ccc483e8061"
  },
  {
    "project_id": "mb-internal-operating-support-013",
    "closure_lane": "source_verification_external_review",
    "vault_href": "vaults/mb-internal-operating-support-013/index.html",
    "required_slot_count": 4,
    "present_slot_count": 0,
    "validation_status": "evidence_missing",
    "promotion_allowed": "no",
    "vault_hash": "d581489338612ee1"
  },
  {
    "project_id": "mb-internal-operating-support-014",
    "closure_lane": "source_verification_external_review",
    "vault_href": "vaults/mb-internal-operating-support-014/index.html",
    "required_slot_count": 4,
    "present_slot_count": 0,
    "validation_status": "evidence_missing",
    "promotion_allowed": "no",
    "vault_hash": "2e05d7fd995c682f"
  },
  {
    "project_id": "mb-internal-operating-support-017",
    "closure_lane": "source_verification_external_review",
    "vault_href": "vaults/mb-internal-operating-support-017/index.html",
    "required_slot_count": 4,
    "present_slot_count": 0,
    "validation_status": "evidence_missing",
    "promotion_allowed": "no",
    "vault_hash": "f305518067c3e236"
  },
  {
    "project_id": "mb-internal-operating-support-018",
    "closure_lane": "source_verification_external_review",
    "vault_href": "vaults/mb-internal-operating-support-018/index.html",
    "required_slot_count": 4,
    "present_slot_count": 0,
    "validation_status": "evidence_missing",
    "promotion_allowed": "no",
    "vault_hash": "7f946d9c0faa3718"
  },
  {
    "project_id": "mb-internal-operating-support-021",
    "closure_lane": "source_verification_external_review",
    "vault_href": "vaults/mb-internal-operating-support-021/index.html",
    "required_slot_count": 4,
    "present_slot_count": 0,
    "validation_status": "evidence_missing",
    "promotion_allowed": "no",
    "vault_hash": "3105caf85d22ce6a"
  },
  {
    "project_id": "mb-internal-operating-support-022",
    "closure_lane": "source_verification_external_review",
    "vault_href": "vaults/mb-internal-operating-support-022/index.html",
    "required_slot_count": 4,
    "present_slot_count": 0,
    "validation_status": "evidence_missing",
    "promotion_allowed": "no",
    "vault_hash": "f61480cd03a8640d"
  },
  {
    "project_id": "mb-internal-operating-support-025",
    "closure_lane": "source_verification_external_review",
    "vault_href": "vaults/mb-internal-operating-support-025/index.html",
    "required_slot_count": 4,
    "present_slot_count": 0,
    "validation_status": "evidence_missing",
    "promotion_allowed": "no",
    "vault_hash": "995eb07b4d30a199"
  },
  {
    "project_id": "mb-internal-operating-support-026",
    "closure_lane": "source_verification_external_review",
    "vault_href": "vaults/mb-internal-operating-support-026/index.html",
    "required_slot_count": 4,
    "present_slot_count": 0,
    "validation_status": "evidence_missing",
    "promotion_allowed": "no",
    "vault_hash": "242f9351e63827e1"
  },
  {
    "project_id": "mb-internal-operating-support-029",
    "closure_lane": "source_verification_external_review",
    "vault_href": "vaults/mb-internal-operating-support-029/index.html",
    "required_slot_count": 4,
    "present_slot_count": 0,
    "validation_status": "evidence_missing",
    "promotion_allowed": "no",
    "vault_hash": "14c472fedb5bb6f2"
  },
  {
    "project_id": "mb-internal-operating-support-030",
    "closure_lane": "source_verification_external_review",
    "vault_href": "vaults/mb-internal-operating-support-030/index.html",
    "required_slot_count": 4,
    "present_slot_count": 0,
    "validation_status": "evidence_missing",
    "promotion_allowed": "no",
    "vault_hash": "c5334fd13d4f1f8e"
  },
  {
    "project_id": "mb-internal-operating-support-033",
    "closure_lane": "source_verification_external_review",
    "vault_href": "vaults/mb-internal-operating-support-033/index.html",
    "required_slot_count": 4,
    "present_slot_count": 0,
    "validation_status": "evidence_missing",
    "promotion_allowed": "no",
    "vault_hash": "d67d753fe71d4ad8"
  },
  {
    "project_id": "mb-internal-operating-support-034",
    "closure_lane": "source_verification_external_review",
    "vault_href": "vaults/mb-internal-operating-support-034/index.html",
    "required_slot_count": 4,
    "present_slot_count": 0,
    "validation_status": "evidence_missing",
    "promotion_allowed": "no",
    "vault_hash": "86846e6c57cfb238"
  },
  {
    "project_id": "mb-redteamlab-proper-handoff-package-2026-04-14",
    "closure_lane": "source_verification_external_review",
    "vault_href": "vaults/mb-redteamlab-proper-handoff-package-2026-04-14/index.html",
    "required_slot_count": 4,
    "present_slot_count": 0,
    "validation_status": "evidence_missing",
    "promotion_allowed": "no",
    "vault_hash": "0e399567a6b071bf"
  },
  {
    "project_id": "mb-rfp-handoff-ch01-02-done",
    "closure_lane": "manuscript_editorial_completion",
    "vault_href": "vaults/mb-rfp-handoff-ch01-02-done/index.html",
    "required_slot_count": 4,
    "present_slot_count": 0,
    "validation_status": "evidence_missing",
    "promotion_allowed": "no",
    "vault_hash": "11159125df125f00"
  },
  {
    "project_id": "mb-wargaming-handoff-pass1",
    "closure_lane": "source_verification_external_review",
    "vault_href": "vaults/mb-wargaming-handoff-pass1/index.html",
    "required_slot_count": 4,
    "present_slot_count": 0,
    "validation_status": "evidence_missing",
    "promotion_allowed": "no",
    "vault_hash": "7ef49c9f26b3fa08"
  },
  {
    "project_id": "native-applied-history-lab",
    "closure_lane": "source_verification_external_review",
    "vault_href": "vaults/native-applied-history-lab/index.html",
    "required_slot_count": 4,
    "present_slot_count": 0,
    "validation_status": "evidence_missing",
    "promotion_allowed": "no",
    "vault_hash": "c77e97cf89bc7c4b"
  },
  {
    "project_id": "native-emt",
    "closure_lane": "source_verification_external_review",
    "vault_href": "vaults/native-emt/index.html",
    "required_slot_count": 4,
    "present_slot_count": 0,
    "validation_status": "evidence_missing",
    "promotion_allowed": "no",
    "vault_hash": "5c60f5e6e4c141dd"
  },
  {
    "project_id": "native-habitat",
    "closure_lane": "source_verification_external_review",
    "vault_href": "vaults/native-habitat/index.html",
    "required_slot_count": 4,
    "present_slot_count": 0,
    "validation_status": "evidence_missing",
    "promotion_allowed": "no",
    "vault_hash": "d3df2e7db58bf9f4"
  },
  {
    "project_id": "native-master-bundle-pages",
    "closure_lane": "source_verification_external_review",
    "vault_href": "vaults/native-master-bundle-pages/index.html",
    "required_slot_count": 4,
    "present_slot_count": 0,
    "validation_status": "evidence_missing",
    "promotion_allowed": "no",
    "vault_hash": "8de3340ce38215ad"
  },
  {
    "project_id": "native-pharm",
    "closure_lane": "source_verification_external_review",
    "vault_href": "vaults/native-pharm/index.html",
    "required_slot_count": 4,
    "present_slot_count": 0,
    "validation_status": "evidence_missing",
    "promotion_allowed": "no",
    "vault_hash": "2e4f17aff1ce9d30"
  },
  {
    "project_id": "native-respite",
    "closure_lane": "source_verification_external_review",
    "vault_href": "vaults/native-respite/index.html",
    "required_slot_count": 4,
    "present_slot_count": 0,
    "validation_status": "evidence_missing",
    "promotion_allowed": "no",
    "vault_hash": "aab70a668f2356e4"
  },
  {
    "project_id": "native-uscri",
    "closure_lane": "source_verification_external_review",
    "vault_href": "vaults/native-uscri/index.html",
    "required_slot_count": 4,
    "present_slot_count": 0,
    "validation_status": "evidence_missing",
    "promotion_allowed": "no",
    "vault_hash": "83b8f2902e2fc2fe"
  },
  {
    "project_id": "red-team-lab",
    "closure_lane": "source_verification_external_review",
    "vault_href": "vaults/red-team-lab/index.html",
    "required_slot_count": 4,
    "present_slot_count": 0,
    "validation_status": "evidence_missing",
    "promotion_allowed": "no",
    "vault_hash": "7576135614bd7fa6"
  }
]