{
  "project_id": "native-western",
  "generated_at": "2026-05-17T01:48:29+00:00",
  "scope": "local_static_package_preview",
  "satisfies_hosted_deployment_gate": false,
  "reason": "This confirms the packaged local static route, not a public hosted Porkbun deployment.",
  "url_path": "/non_overlap_runtime_slices/apps/native-western/index.html",
  "http_status": 200,
  "desktop_screenshot": {
    "url": "http://127.0.0.1:1882/non_overlap_runtime_slices/apps/native-western/index.html",
    "output_file": "desktop_screenshot.png",
    "width": 1280,
    "height": 820,
    "returncode": 0,
    "stderr_tail": " from : [local-path-redacted]",
    "exists": true,
    "size_bytes": 89997,
    "sha256": "43a8d9bd1c1ba20b6c494f2be6efbdd178b126e5cc8269e223df3bf3641b597f"
  },
  "mobile_screenshot": {
    "url": "http://127.0.0.1:1882/non_overlap_runtime_slices/apps/native-western/index.html",
    "output_file": "mobile_screenshot.png",
    "width": 390,
    "height": 780,
    "returncode": 0,
    "stderr_tail": "essional_20260504_190328_native_pages\\non_overlap_residual_evidence_vaults\\vaults\\native-western\\mobile_screenshot.png\n[39956:46408:0516/215839.756:ERROR:extensions\\common\\file_util.cc:144] Moving extension from : [local-path-redacted]",
    "exists": true,
    "size_bytes": 53857,
    "sha256": "2e6f7b5c36a15448ff7e5974a69b76de275322905567352c2f47154490cb7681"
  }
}
