{
  "project_id": "bias-atlas",
  "closure_lane": "live_case_calibration",
  "generated_at": "2026-05-15T21:53:39+00:00",
  "local_automated_evidence_items": [
    {
      "name": "closure packet exists",
      "status": "pass",
      "evidence": "closure_packet.json present"
    },
    {
      "name": "required evidence list exists",
      "status": "pass",
      "evidence": "4 required evidence items"
    },
    {
      "name": "completion tests list exists",
      "status": "pass",
      "evidence": "3 completion tests"
    },
    {
      "name": "default closure status remains not closed",
      "status": "pass",
      "evidence": "not_closed"
    },
    {
      "name": "calibration rehearsal cases generated",
      "status": "pass",
      "evidence": "three synthetic rehearsal cases; not live-case evidence"
    }
  ],
  "generated_artifacts": [
    {
      "artifact": "synthetic_calibration_rehearsal_cases",
      "count": 3,
      "status": "generated"
    }
  ],
  "residual_gates": [
    "live or realistic cases",
    "calibration record",
    "expert or reviewer check"
  ],
  "local_automated_status": "synthetic_rehearsal_ready_live_calibration_open",
  "underlying_project_fully_operational": false,
  "promotion_rule": "Do not promote to fully operational until residual gates are satisfied with retained evidence.",
  "evidence_hash": "eb33a2cf4523f5e8"
}